sciunit2/__init__.py
sciunit2/api.py
sciunit2/archiver.py
sciunit2/cdelog.py
sciunit2/cli.py
sciunit2/config.py
sciunit2/core.py
sciunit2/credentials.py
sciunit2/ephemeral.py
sciunit2/exceptions.py
sciunit2/records.py
sciunit2/setup.py
sciunit2/timestamp.py
sciunit2/util.py
sciunit2/version.py
sciunit2/version_control.py
sciunit2/wget.py
sciunit2/workspace.py
sciunit2/command/__init__.py
sciunit2/command/commit.py
sciunit2/command/context.py
sciunit2/command/copy.py
sciunit2/command/create.py
sciunit2/command/diff.py
sciunit2/command/given.py
sciunit2/command/list.py
sciunit2/command/mixin.py
sciunit2/command/open.py
sciunit2/command/push.py
sciunit2/command/repeat.py
sciunit2/command/rm.py
sciunit2/command/show.py
sciunit2/command/sort.py
sciunit2/command/exec_/__init__.py
sciunit2/command/exec_/sciunit
sciunit2/command/post_install/__init__.py
sciunit2/command/post_install/sciunit-completion.bash
sciunit2/command/post_install/sciunit-completion.tcsh
sciunit2/libexec/__init__.py
sciunit2/libexec/ptu
sciunit2/libexec/scripter
sciunit2/libexec/vv
sciunit2/libexec/__pycache__/__init__.cpython-36.pyc
sciunit2/sharing/__init__.py
sciunit2/sharing/article.py
sciunit2/sharing/hydroshare.py
sciunit2/sharing/terminal.py
sciunit2/wrapper/__init__.py
sciunit2-0.4.post56.dev130522793.data/data/man/man1/sciunit.1.gz
sciunit2-0.4.post56.dev130522793.dist-info/DESCRIPTION.rst
sciunit2-0.4.post56.dev130522793.dist-info/METADATA
sciunit2-0.4.post56.dev130522793.dist-info/RECORD
sciunit2-0.4.post56.dev130522793.dist-info/WHEEL
sciunit2-0.4.post56.dev130522793.dist-info/entry_points.txt
sciunit2-0.4.post56.dev130522793.dist-info/metadata.json
sciunit2-0.4.post56.dev130522793.dist-info/top_level.txt
tests/__init__.py
tests/sciunit.py
tests/test_api.py
tests/test_archiver.py
tests/test_basics.py
tests/test_commit.py
tests/test_config.py
tests/test_copy.py
tests/test_create.py
tests/test_exec.py
tests/test_given.py
tests/test_hydroshare.py
tests/test_list.py
tests/test_open.py
tests/test_post_install.py
tests/test_push.py
tests/test_repeat.py
tests/test_rm.py
tests/test_show.py
tests/test_sort.py
tests/test_workspace.py
tests/testit.py
