Metadata-Version: 2.1
Name: sciunit2
Version: 0.4.post56.dev130522793
Summary: Sciunit command line
Home-page: https://sciunit.run/
Author: Zhihao Yuan, Tanu Malik
Author-email: pr@sciunit.run
Maintainer: Zhihao Yuan
Maintainer-email: lichray@gmail.com
License: BSD
Project-URL: Homepage, https://sciunit.run/
Project-URL: Documentation, https://sciunit.run/docs/
Project-URL: Source, https://bitbucket.org/geotrust/sciunit2
Keywords: sciunit,reproducibility,container,versioning
Platform: UNKNOWN
Classifier: Development Status :: 4 - Beta
Classifier: License :: OSI Approved :: BSD License
Classifier: Operating System :: POSIX :: Linux
Classifier: Programming Language :: Python :: 3.6
Classifier: Programming Language :: Python :: Implementation :: PyPy
Classifier: Intended Audience :: Science/Research
Requires-Dist: setuptools
Requires-Dist: tzlocal
Requires-Dist: utcdatetime
Requires-Dist: zipfile2
Requires-Dist: scandir
Requires-Dist: retry
Requires-Dist: humanfriendly
Requires-Dist: configobj
Requires-Dist: hs-restclient
Requires-Dist: contextlib2
Requires-Dist: tqdm (>=4.17.1)
Requires-Dist: backports.tempfile
